drf_fields_limiting/__init__.py
drf_fields_limiting/constants.py
drf_fields_limiting/mixins.py
drf_fields_limiting/operations.py
drf_fields_limiting/serializers.py
drf_fields_limiting/views.py
drf_fields_limiting/viewsets.py
tests/__init__.py
tests/models.py
tests/test_views.py
tests/test_viewsets.py
drf_fields_limiting-1.0.0.dist-info/METADATA
drf_fields_limiting-1.0.0.dist-info/WHEEL
drf_fields_limiting-1.0.0.dist-info/top_level.txt
drf_fields_limiting-1.0.0.dist-info/RECORD
