Metadata-Version: 2.1
Name: drf-fields-limiting
Version: 1.0.0
Summary: This package provides utils for Django Rest Framework API views and serializers for limiting fields returned in responses thus limiting size and complexity of database requests.
Author: IIIT
Author-email: github@iiit.pl
License: UNKNOWN
Platform: UNKNOWN
Classifier: Environment :: Web Environment
Classifier: Framework :: Django
Classifier: Intended Audience :: Developers
Classifier: Operating System :: OS Independent
Classifier: Programming Language :: Python
Classifier: Programming Language :: Python :: 3.6
Classifier: Programming Language :: Python :: 3.7
Classifier: Programming Language :: Python :: 3.8
Classifier: Programming Language :: Python :: 3.9
Requires-Dist: Django (<3.3,>=2.2.0)
Requires-Dist: djangorestframework (<3.14,>=3.7.4)
